cherry_tree_writer-0.41.dist-info/licenses/LICENSE
ctb_writer/__init__.py
ctb_writer/cherry_tree.py
ctb_writer/cherry_tree_link.py
ctb_writer/cherry_tree_node.py
ctb_writer/cherry_tree_rows.py
ctb_writer/node_builder.py
ctb_writer/assets/__init__.py
ctb_writer/beautify/__init__.py
ctb_writer/beautify/__main__.py
ctb_writer/beautify/text.py
ctb_writer/beautify/text_parser.py
ctb_writer/icons/__init__.py
ctb_writer/icons/__main__.py
ctb_writer/icons/node_icon.py
ctb_writer/styles/__init__.py
ctb_writer/styles/__main__.py
cherry_tree_writer-0.41.dist-info/METADATA
cherry_tree_writer-0.41.dist-info/WHEEL
cherry_tree_writer-0.41.dist-info/top_level.txt
cherry_tree_writer-0.41.dist-info/RECORD
