Metadata-Version: 2.4
Name: cherry_tree_writer
Version: 0.41
Summary: Minimalist Python library for writting cherrytree document
Author: Guilhem RIOUX
License-File: LICENSE
Dynamic: author
Dynamic: description
Dynamic: description-content-type
Dynamic: license-file
Dynamic: summary
